setup.py
cidrtip/__init__.py
cidrtip/cidr.py
cidrtip.egg-info/PKG-INFO
cidrtip.egg-info/SOURCES.txt
cidrtip.egg-info/dependency_links.txt
cidrtip.egg-info/requires.txt
cidrtip.egg-info/top_level.txt