Metadata-Version: 2.1
Name: cidrtip
Version: 0.1
Requires-Dist: ipaddress
